mammotion_sdk/client.cpython-39-x86_64-linux-gnu.so
mammotion_sdk/parser.cpython-39-x86_64-linux-gnu.so
mammotion_sdk/device_message/demo.cpython-39-x86_64-linux-gnu.so
mammotion_sdk/device_message/login.cpython-39-x86_64-linux-gnu.so
mammotion_sdk/device_message/bp/Luba_msg_pb2.cpython-39-x86_64-linux-gnu.so
mammotion_sdk/device_message/bp/Luba_mul_pb2.cpython-39-x86_64-linux-gnu.so
mammotion_sdk/device_message/bp/basestation_pb2.cpython-39-x86_64-linux-gnu.so
mammotion_sdk/device_message/bp/common_pb2.cpython-39-x86_64-linux-gnu.so
mammotion_sdk/device_message/bp/dd.cpython-39-x86_64-linux-gnu.so
mammotion_sdk/device_message/bp/dev_net_pb2.cpython-39-x86_64-linux-gnu.so
mammotion_sdk/device_message/bp/esp_driver_pb2.cpython-39-x86_64-linux-gnu.so
mammotion_sdk/device_message/bp/mctrl_driver_pb2.cpython-39-x86_64-linux-gnu.so
mammotion_sdk/device_message/bp/mctrl_nav_pb2.cpython-39-x86_64-linux-gnu.so
mammotion_sdk/device_message/bp/mctrl_ota_pb2.cpython-39-x86_64-linux-gnu.so
mammotion_sdk/device_message/bp/mctrl_pept_pb2.cpython-39-x86_64-linux-gnu.so
mammotion_sdk/device_message/bp/mctrl_sys_pb2.cpython-39-x86_64-linux-gnu.so
mammotion_sdk/device_message/bp/pdt_pb2.cpython-39-x86_64-linux-gnu.so
mammotion_sdk_harry-1.0.7.dist-info/METADATA
mammotion_sdk_harry-1.0.7.dist-info/WHEEL
mammotion_sdk_harry-1.0.7.dist-info/top_level.txt
mammotion_sdk_harry-1.0.7.dist-info/RECORD
