Metadata-Version: 2.4
Name: mammotion-sdk-harry
Version: 1.0.7
Summary: Mammotion's SDK for the Home Assistant project
Author: Harry
Classifier: Programming Language :: Python :: 3
Classifier: License :: OSI Approved :: MIT License
Classifier: Operating System :: OS Independent
Requires-Python: >=3.7
Requires-Dist: protobuf
Dynamic: author
Dynamic: classifier
Dynamic: description
Dynamic: description-content-type
Dynamic: requires-dist
Dynamic: requires-python
Dynamic: summary
